__init__.py
simplerabbit/__init__.py
simplerabbit/monitor.py
simplerabbit/rabbit_base.py
simplerabbit/receiver.py
simplerabbit/sender.py
simplerabbit/util/__init__.py
simplerabbit/util/logger.py
simplerabbit-0.0.15.dist-info/METADATA
simplerabbit-0.0.15.dist-info/WHEEL
simplerabbit-0.0.15.dist-info/top_level.txt
simplerabbit-0.0.15.dist-info/RECORD
