Metadata-Version: 2.1
Name: simplerabbit
Version: 0.0.15
Summary: Simple RabbitMQ library
Author-email: Phuong Do <phdo@energidanmark.dk>
Project-URL: Homepage, https://github.com/Energidanmark/simplerabbit
Project-URL: Bug Tracker, https://github.com/Energidanmark/simplerabbit/issues
Classifier: Programming Language :: Python :: 3
Classifier: License :: OSI Approved :: MIT License
Classifier: Operating System :: OS Independent
Requires-Python: >=3.7
